Workbook

Sheet Summary
A1: Server BOM to host Mistral Medium 3.5 - summary
A2: Mistral Medium 3.5: 128B dense, vision, 256K context, open weights (Modified MIT, 2026-04-29). FP8 weights ~134 GB; Mistral's floor is 'as few as four GPUs'. Prices are Oct 2026 estimates ex VAT; blue cells on the Assumptions and tier sheets are editable.
A4: Tier | B4: Runs | C4: GPU VRAM (GB) | D4: Capex ex VAT (EUR) | E4: Capex incl. VAT (EUR) | F4: Peak power (W) | G4: Electricity / month (EUR) | H4: TCO / month (EUR, ex VAT)
A5: A - 4x RTX PRO 6000 Blackwell (recommended on-prem) | B5: Mistral Medium 3.5 FP8, 64K-128K ctx | C5: ='Tier A - Medium on-prem'!F30 | D5: ='Tier A - Medium on-prem'!F19 | E5: ='Tier A - Medium on-prem'!F21 | F5: ='Tier A - Medium on-prem'!F24 | G5: ='Tier A - Medium on-prem'!F26 | H5: ='Tier A - Medium on-prem'!F28
A6: B - 1x RTX 5090 workstation (local fallback) | B6: Mistral Small 3.2 24B only | C6: ='Tier B - Small workstation'!F28 | D6: ='Tier B - Small workstation'!F17 | E6: ='Tier B - Small workstation'!F19 | F6: ='Tier B - Small workstation'!F22 | G6: ='Tier B - Small workstation'!F24 | H6: ='Tier B - Small workstation'!F26
A7: C - 4x H100 80 GB (reference) | B7: Mistral Medium 3.5 FP8 | C7: ='Tier C - H100 reference'!F27 | D7: ='Tier C - H100 reference'!F16 | E7: ='Tier C - H100 reference'!F18 | F7: ='Tier C - H100 reference'!F21 | G7: ='Tier C - H100 reference'!F23 | H7: ='Tier C - H100 reference'!F25
A9: Recommendation
A10: Buy Tier A only once monthly API or rental spend passes the break-even on the 'Cloud vs buy' sheet. Until then keep hosted mistral-medium-latest (measured ~0.01 EUR per page) and put Tier B on the desk as the local, swappable fallback. Tier C costs about twice Tier A for the same model fit.
A12: Sheets: Assumptions (inputs) · Tier A/B/C (line items) · Cloud vs buy · Notes & sources

Sheet Assumptions
A1: Assumptions (edit the blue cells)
A2: All prices in EUR excluding VAT, estimates as of 2026-10-17. Replace with supplier quotes before ordering.
A4: Parameter | B4: Value | C4: Note / source
A5: VAT rate (Germany) | B5: 0.19 | C5: German standard rate.
A6: Electricity price (EUR per kWh) | B6: 0.3 | C6: Typical German commercial tariff 2026, user to confirm.
A7: Contingency on hardware (spares, cables, shipping) | B7: 0.05 | C7: Rule of thumb.
A8: Amortisation period (months) | B8: 36 | C8: Three years, matches the warranty line.
A9: Operating hours per month | B9: 730 | C9: 24/7 = 730 h. Lower it if the box is switched off at night.
A10: Average load factor (share of peak power while on) | B10: 0.4 | C10: Inference boxes idle a lot; 40 % is a mid estimate.
A11: Cloud rental: 4x H100 80 GB (EUR per hour) | B11: 12 | C11: On-demand range 10-16 EUR/h across Lambda, RunPod, Hetzner-class providers, Oct 2026.
A12: Cloud rental: 4x RTX PRO 6000 96 GB (EUR per hour) | B12: 7 | C12: On-demand estimate, Oct 2026.
A13: Cloud rental: 1x RTX 5090 / 4090 (EUR per hour) | B13: 0.6 | C13: On-demand estimate, Oct 2026.
A14: Mistral API cost per page (EUR) | B14: 0.01 | C14: Measured: 39 vision calls to mistral-medium-latest cost 0.39 USD on the corpus replay (bh3 README, 2026-10-17).
A15: Pages processed per month | B15: 5000 | C15: Scenario input: the challenge corpus is 1,034 pages.
A17: Legend
A18: Blue text on yellow = input you can change. Black = formula. Green = value pulled from another sheet.

Sheet Tier A - Medium on-prem
A1: Tier A - Mistral Medium 3.5 on-prem (4x RTX PRO 6000 Blackwell)
A2: Runs Mistral Medium 3.5 128B at FP8 (the official checkpoint) with 384 GB VRAM: ~134 GB weights plus room for a 64K-128K KV cache and the vision tower. Cheapest sane on-prem build.
A4: # | B4: Item | C4: Spec / notes | D4: Qty | E4: Unit price (EUR ex VAT) | F4: Line total (EUR ex VAT) | G4: Peak power per unit (W) | H4: Source / assumption
A5: 1 | B5: NVIDIA RTX PRO 6000 Blackwell Server Edition 96 GB GDDR7 | C5: passive, 600 W, PCIe 5.0 x16, dual slot | D5: 4 | E5: 8900 | F5: =D5*E5 | G5: 600 | H5: Street 6,999-8,990 EUR ex VAT on eBay.de / Arvutitark; Servermall 12,893 EUR ex VAT; SHI list 17,628 EUR. Budget the mid value.
A6: 2 | B6: 4U GPU server barebone, 4-8 double-width GPU slots | C6: e.g. Supermicro AS-4125GS-TNRT or ASRock Rack 4U, 2x 2,700 W redundant Titanium PSU, 8x NVMe bays, 2x 10 GbE onboard, rails | D6: 1 | E6: 7500 | F6: =D6*E6 | G6: 500 | H6: Reseller B2B estimate; public listings are stale. Get a quote from Supermicro / ASRock Rack partner (e.g. Thomas-Krenn, Delta Computer).
A7: 3 | B7: AMD EPYC 9354 32-core CPU | C7: Zen 4, 128 PCIe 5.0 lanes; one socket is enough for inference | D7: 1 | E7: 2800 | F7: =D7*E7 | G7: 0 | H7: Distributor estimate.
A8: 4 | B8: DDR5-4800 ECC RDIMM 64 GB | C8: 6 modules = 384 GB, one DIMM per channel (6 of 12 channels) | D8: 6 | E8: 280 | F8: =D8*E8 | G8: 0 | H8: Model loading and page cache; 256 GB+ recommended by Mistral self-host guides.
A9: 5 | B9: Enterprise NVMe U.2 3.84 TB | C9: model weights (~140 GB), work cache, page images; mirror as RAID 1 | D9: 2 | E9: 450 | F9: =D9*E9 | G9: 0 | H9: Kioxia CD8 / Micron 7450 class.
A10: 6 | B10: Boot SSD M.2 1 TB | C10: OS and containers | D10: 1 | E10: 120 | F10: =D10*E10 | G10: 0
A11: 7 | B11: NIC 25 GbE dual-port (optional) | C11: Mellanox ConnectX-6 Lx; onboard 10 GbE is enough for a single box | D11: 1 | E11: 450 | F11: =D11*E11 | G11: 0 | H11: Optional; set qty 0 if the onboard 10 GbE suffices.
A12: 8 | B12: UPS 3 kVA online double conversion, rack 2U | C12: covers 2.9 kW peak for a clean shutdown | D12: 1 | E12: 1800 | F12: =D12*E12 | G12: 0 | H12: APC SRT3000 / Eaton 9PX class.
A13: 9 | B13: 12U rack / enclosure | C13: skip if a rack exists | D13: 1 | E13: 500 | F13: =D13*E13 | G13: 0 | H13: Optional.
A14: 10 | B14: Assembly, burn-in, OS + vLLM install | C14: Ubuntu 24.04, NVIDIA driver, Docker, vLLM nightly, model download | D14: 1 | E14: 1500 | F14: =D14*E14 | G14: 0 | H14: Integrator labour estimate, ~2 days.
A15: 11 | B15: 3-year on-site warranty / support | C15: server and GPUs | D15: 1 | E15: 2500 | F15: =D15*E15 | G15: 0 | H15: Typical NBD on-site uplift.
A16: 12 | B16: Software: Ubuntu Server, vLLM, Mistral Medium 3.5 weights | C16: Modified MIT licence, free | D16: 1 | E16: 0 | F16: =D16*E16 | G16: 0 | H16: mistralai/Mistral-Medium-3.5-128B on Hugging Face.
B17: Hardware subtotal (ex VAT) | F17: =SUM(F5:F16)
B18: Contingency (spares, cables, shipping) | C18: rate from Assumptions | E18: =Assumptions!$B$7 | F18: =F17*E18
B19: Total capex (ex VAT) | F19: =F17+F18
B20: VAT | E20: =Assumptions!$B$5 | F20: =F19*E20
B21: Total capex (incl. VAT) | F21: =F19+F20
B23: Power and running cost
B24: Peak system power (W) | F24: =SUMPRODUCT(D5:D16,G5:G16)
B25: Average draw (W) = peak x load factor | E25: =Assumptions!$B$10 | F25: =F24*E25
B26: Electricity per month (EUR) | C26: avg W / 1000 x hours x EUR/kWh | F26: =F25/1000*Assumptions!$B$9*Assumptions!$B$6
B27: Capex amortised per month (EUR, ex VAT) | F27: =F19/Assumptions!$B$8
B28: Total cost of ownership per month (EUR, ex VAT) | F28: =F26+F27
B30: Total GPU VRAM (GB) | F30: 384 | H30: GPU count x VRAM per card.

Sheet Tier B - Small workstation
A1: Tier B - Mistral Small 3.2 workstation (1x RTX 5090)
A2: Runs Mistral Small 3.2 24B (vision) at FP8/Q4 on one 32 GB card as the local fallback. Does NOT run Mistral Medium 3.5.
A4: # | B4: Item | C4: Spec / notes | D4: Qty | E4: Unit price (EUR ex VAT) | F4: Line total (EUR ex VAT) | G4: Peak power per unit (W) | H4: Source / assumption
A5: 1 | B5: NVIDIA GeForce RTX 5090 32 GB | C5: 575 W, consumer card | D5: 1 | E5: 2300 | F5: =D5*E5 | G5: 575 | H5: Street price Oct 2026, ex VAT.
A6: 2 | B6: AMD Ryzen 9 9950X 16-core | D6: 1 | E6: 550 | F6: =D6*E6 | G6: 170
A7: 3 | B7: X870E ATX motherboard | C7: PCIe 5.0 x16, 2.5/10 GbE | D7: 1 | E7: 350 | F7: =D7*E7 | G7: 0
A8: 4 | B8: DDR5-5600 48 GB (2x = 96 GB) | C8: non-ECC desktop | D8: 2 | E8: 175 | F8: =D8*E8 | G8: 0
A9: 5 | B9: NVMe M.2 2 TB | C9: models and page cache | D9: 1 | E9: 150 | F9: =D9*E9 | G9: 0
A10: 6 | B10: PSU 1,200 W ATX 3.1 (12V-2x6) | D10: 1 | E10: 220 | F10: =D10*E10 | G10: 0
A11: 7 | B11: Tower case with airflow | D11: 1 | E11: 150 | F11: =D11*E11 | G11: 0
A12: 8 | B12: CPU cooler 360 mm AIO | D12: 1 | E12: 130 | F12: =D12*E12 | G12: 0
A13: 9 | B13: Assembly + Ubuntu / Ollama or vLLM install | D13: 1 | E13: 150 | F13: =D13*E13 | G13: 0 | H13: In-house, half a day.
A14: 10 | B14: Software: Mistral Small 3.2 weights | C14: Apache 2.0, free | D14: 1 | E14: 0 | F14: =D14*E14 | G14: 0 | H14: mistralai/Mistral-Small-3.2-24B-Instruct-2506.
B15: Hardware subtotal (ex VAT) | F15: =SUM(F5:F14)
B16: Contingency (spares, cables, shipping) | C16: rate from Assumptions | E16: =Assumptions!$B$7 | F16: =F15*E16
B17: Total capex (ex VAT) | F17: =F15+F16
B18: VAT | E18: =Assumptions!$B$5 | F18: =F17*E18
B19: Total capex (incl. VAT) | F19: =F17+F18
B21: Power and running cost
B22: Peak system power (W) | F22: =SUMPRODUCT(D5:D14,G5:G14)
B23: Average draw (W) = peak x load factor | E23: =Assumptions!$B$10 | F23: =F22*E23
B24: Electricity per month (EUR) | C24: avg W / 1000 x hours x EUR/kWh | F24: =F23/1000*Assumptions!$B$9*Assumptions!$B$6
B25: Capex amortised per month (EUR, ex VAT) | F25: =F17/Assumptions!$B$8
B26: Total cost of ownership per month (EUR, ex VAT) | F26: =F24+F25
B28: Total GPU VRAM (GB) | F28: 32 | H28: GPU count x VRAM per card.

Sheet Tier C - H100 reference
A1: Tier C - Reference: 4x H100 80 GB node
A2: What the 'four GPUs' in Mistral's announcement usually means. Same model fit as Tier A (320 GB VRAM, FP8) at datacenter pricing. Listed for comparison; not recommended for a first box.
A4: # | B4: Item | C4: Spec / notes | D4: Qty | E4: Unit price (EUR ex VAT) | F4: Line total (EUR ex VAT) | G4: Peak power per unit (W) | H4: Source / assumption
A5: 1 | B5: NVIDIA H100 80 GB PCIe | C5: 350 W, passive, NVLink bridge optional | D5: 4 | E5: 25000 | F5: =D5*E5 | G5: 350 | H5: Street 22,000-30,000 EUR ex VAT in 2026, estimate.
A6: 2 | B6: 4U GPU server barebone (as Tier A) | C6: 2x 2,700 W redundant PSU | D6: 1 | E6: 7500 | F6: =D6*E6 | G6: 500 | H6: Same chassis as Tier A.
A7: 3 | B7: AMD EPYC 9354 32-core CPU | D7: 1 | E7: 2800 | F7: =D7*E7 | G7: 0
A8: 4 | B8: DDR5-4800 ECC RDIMM 64 GB | C8: 6 modules = 384 GB | D8: 6 | E8: 280 | F8: =D8*E8 | G8: 0
A9: 5 | B9: Enterprise NVMe U.2 3.84 TB | C9: RAID 1 | D9: 2 | E9: 450 | F9: =D9*E9 | G9: 0
A10: 6 | B10: Boot SSD M.2 1 TB | D10: 1 | E10: 120 | F10: =D10*E10 | G10: 0
A11: 7 | B11: UPS 3 kVA online, rack 2U | D11: 1 | E11: 1800 | F11: =D11*E11 | G11: 0
A12: 8 | B12: Assembly, burn-in, OS + vLLM install | D12: 1 | E12: 1500 | F12: =D12*E12 | G12: 0
A13: 9 | B13: 3-year on-site warranty / support | D13: 1 | E13: 2500 | F13: =D13*E13 | G13: 0
B14: Hardware subtotal (ex VAT) | F14: =SUM(F5:F13)
B15: Contingency (spares, cables, shipping) | C15: rate from Assumptions | E15: =Assumptions!$B$7 | F15: =F14*E15
B16: Total capex (ex VAT) | F16: =F14+F15
B17: VAT | E17: =Assumptions!$B$5 | F17: =F16*E17
B18: Total capex (incl. VAT) | F18: =F16+F17
B20: Power and running cost
B21: Peak system power (W) | F21: =SUMPRODUCT(D5:D13,G5:G13)
B22: Average draw (W) = peak x load factor | E22: =Assumptions!$B$10 | F22: =F21*E22
B23: Electricity per month (EUR) | C23: avg W / 1000 x hours x EUR/kWh | F23: =F22/1000*Assumptions!$B$9*Assumptions!$B$6
B24: Capex amortised per month (EUR, ex VAT) | F24: =F16/Assumptions!$B$8
B25: Total cost of ownership per month (EUR, ex VAT) | F25: =F23+F24
B27: Total GPU VRAM (GB) | F27: 320 | H27: GPU count x VRAM per card.

Sheet Cloud vs buy
A1: Cloud rental and API versus owning the box
A2: Monthly figures. Rental and API rows use the Assumptions sheet; on-prem rows use the BOM sheets.
A4: Option | B4: Runs Mistral Medium 3.5? | C4: EUR per month (ex VAT) | D4: Basis | E4: Break-even vs owning (months)
A6: Own Tier A (4x RTX PRO 6000), TCO | B6: Yes | C6: ='Tier A - Medium on-prem'!F28 | D6: electricity + capex / amortisation months
A7: Own Tier C (4x H100), TCO | B7: Yes | C7: ='Tier C - H100 reference'!F25 | D7: electricity + capex / amortisation months
A8: Own Tier B (1x RTX 5090), TCO | B8: No (Small 3.2 only) | C8: ='Tier B - Small workstation'!F26 | D8: electricity + capex / amortisation months
A9: Rent 4x H100 on demand | B9: Yes | C9: =Assumptions!$B$11*Assumptions!$B$9 | D9: EUR/h x operating hours | E9: ='Tier C - H100 reference'!F16/C9
A10: Rent 4x RTX PRO 6000 on demand | B10: Yes | C10: =Assumptions!$B$12*Assumptions!$B$9 | D10: EUR/h x operating hours | E10: ='Tier A - Medium on-prem'!F19/C10
A11: Rent 1x RTX 5090 on demand | B11: No (Small 3.2 only) | C11: =Assumptions!$B$13*Assumptions!$B$9 | D11: EUR/h x operating hours | E11: ='Tier B - Small workstation'!F17/C11
A12: Mistral API (mistral-medium-latest), pay per page | B12: Yes (hosted) | C12: =Assumptions!$B$14*Assumptions!$B$15 | D12: measured EUR/page x pages per month | E12: ='Tier A - Medium on-prem'!F19/C12
A14: Break-even = capex of the comparable owned tier / monthly rental or API spend. Below the amortisation period means buying is cheaper than renting at that usage.
A15: Pages per month needed for the API to cost as much as owning Tier A: | C15: ='Tier A - Medium on-prem'!F28/Assumptions!$B$14

Sheet Notes & sources
A1: Notes and sources
A3: Topic | B3: Note | C3: Source
A4: Model facts | B4: Mistral Medium 3.5: 128B dense, vision encoder (max image 1540x1540), 256K context, FP8 checkpoint ~134 GB, Modified MIT licence, released 2026-04-29. vLLM nightly required (not in a stable release yet). HF: mistralai/Mistral-Medium-3.5-128B. | C4: https://recipes.vllm.ai/mistralai/Mistral-Medium-3.5-128B
A5: Model facts | B5: NVIDIA model card: input text + image, output text, Modified MIT. | C5: https://build.nvidia.com/mistralai/mistral-medium-3.5-128b/modelcard
A6: Sizing | B6: FP8 ~128 GB weights, ~147 GB minimum before KV cache; BF16 ~256 GB; INT4 ~64 GB. 4x H100 80 GB called the 'sweet spot'. vllm serve example with --tensor-parallel-size 4 --quantization fp8 --max-model-len 65536. | C6: https://www.spheron.network/blog/mistral-medium-3-5-gpu-requirements/
A7: Sizing | B7: Mistral: self-host on 'as few as four GPUs'. Suggested: 4x H100 80 GB, 4x H200 141 GB, or 4x RTX PRO 6000 Blackwell 96 GB; 256 GB+ system RAM; 10 GbE; 2,500 W+ under load. | C7: https://vrlatech.com/mistral-medium-3-5/
A8: Sizing | B8: vLLM recipe recommends 8x H200 (TP 8) or 4x B200 for full 256K context; a single B200 / MI300X fits the weights but leaves little KV cache. | C8: https://recipes.vllm.ai/mistralai/Mistral-Medium-3.5-128B
A9: GPU price | B9: RTX PRO 6000 Blackwell Server Edition 96 GB: 6,999 EUR ex VAT (eBay.de, sold), 8,854 EUR (Arvutitark), 8,990 EUR (eBay.de), 12,893 EUR ex VAT (Servermall), 17,628 EUR list (SHI). | C9: https://servermall.com/catalog/gpu/nvidia-rtx-pro-6000-blackwell-server-edition/
A10: GPU price | B10: Arvutitark listing, 8,854.40 EUR. | C10: https://www.arvutitark.ee/en/pc-components/graphics-cards-vga/nvidia-rtx-pro-6000-blackwell-server-edition-96-gb-gddr7-1486083
A11: GPU price | B11: H100 80 GB PCIe: 22,000-30,000 EUR ex VAT street in 2026 (estimate, no public 2026 listing found; Servermall 6x H100 system 301,469 EUR). | C11: https://servermall.com/catalog/servers/supermicro-as-4124gs-tnr-24sff/
A12: Chassis | B12: Public 4x GPU barebone listings are stale or out of stock; the 7,500 EUR line is a reseller estimate. Ask Thomas-Krenn / Delta Computer / Supermicro partners for a quote. | C12: https://www.neweggbusiness.com/s/server-barebones/id-8/3?local=y
A13: Fallback model | B13: Mistral Small 3.2 24B (vision, Apache 2.0): ~14-21 GB at Q4 depending on context, ~26 GB at Q8; fits one 24-32 GB card. | C13: https://willitrunai.com/models/hf-unsloth--mistral-small-3-2-24b-instruct-2506-gguf
A14: Project measurement | B14: Corpus replay 2026-10-17: 39 vision calls to mistral-medium-latest = 0.39 USD, i.e. ~0.01 EUR per page. Medium downscales images to ~1540 px, matching the model card limit. | C14: bh3/README.md (local)
A15: Caveat | B15: Rental prices, electricity, labour and warranty lines are estimates and not quotes. Replace blue cells with supplier figures before any purchase decision. Formulas recalculate automatically in Excel on open.
